{
  "check-in-inspection-dubai": {
    "slug": "check-in-inspection-dubai",
    "label": "चेक-इन निरीक्षण",
    "fileName": "check-in-inspection-dubai",
    "metaTitle": "दुबई चेक-इन निरीक्षण · मुफ़्त RDC में मान्य रिपोर्ट्स · Snagify",
    "metaDescription": "एक मुफ़्त, RDC में मान्य चेक-इन निरीक्षण के साथ मूव-इन पर अपने दुबई अपार्टमेंट का दस्तावेज़ीकरण करें। AI तस्वीर विश्लेषण, दोहरे हस्ताक्षर, 20 मिनट। 40+ दुबई एजेंसियों द्वारा उपयोग किया जाता है।",
    "keywords": "चेक-इन निरीक्षण दुबई, मूव-इन निरीक्षण दुबई, दुबई चेक इन रिपोर्ट, किराया चेक इन दुबई, ejari चेक इन निरीक्षण",
    "eyebrow": "उपयोग का मामला",
    "headline": "दुबई में चेक-इन निरीक्षण।",
    "headlineHighlight": "दुबई में।",
    "subheadline": "बिना दस्तावेज़ीकरण वाला मूव-इन दुबई में जमानत राशि खोने का सबसे बड़ा कारण है। एक उचित चेक-इन निरीक्षण वह आधार रेखा निर्धारित करता है जो पूरे पट्टे के लिए मकान मालिक और किरायेदार दोनों की रक्षा करती है।",
    "what": [
      "चेक-इन निरीक्षण किरायेदार के मूव-इन के दिन एक किराये की संपत्ति का दस्तावेज़ी दौरा है। यह कमरा-दर-कमरा, हर फ़िक्स्चर और हर उपकरण की सटीक स्थिति को कैद करता है इससे पहले कि कोई भी इकाई में रहे।",
      "दुबई में, चेक-इन निरीक्षण एक महत्वपूर्ण उद्देश्य पूरा करता है: यह एक आधार रेखा बनाता है जिसे Rental Dispute Center (RDC) मूव-आउट के समय तुलना कर सकता है। उस आधार रेखा के बिना, चेक-आउट पर हर खरोंच, दाग़ या क्षति 'कहासुनी' का तर्क बन जाती है जो लगभग हमेशा किरायेदार की जमानत राशि खोने पर समाप्त होती है।",
      "Snagify चेक-इन को मुफ़्त बनाता है। हम चाहते हैं कि दुबई के हर किरायेदार और मकान मालिक को यह सुरक्षा मिले, चाहे वे कभी फिर से Snagify का उपयोग करें या नहीं।"
    ],
    "scenarios": [
      {
        "title": "आपने अभी-अभी अपना Ejari साइन किया और चाबियाँ ले लीं।",
        "body": "जिस दिन आप मूव-इन करते हैं वह अपार्टमेंट को उसकी मूल स्थिति में दस्तावेज़ी करने का एकमात्र मौक़ा है। दो हफ़्ते रुकें और आप अब साबित नहीं कर पाएँगे कि आपके आगमन से पहले वहाँ क्या था।"
      },
      {
        "title": "आप पहली बार एक इकाई किराए पर दे रहे मकान मालिक हैं।",
        "body": "एक दस्तावेज़ी चेक-इन के बिना, आपके पास मूव-आउट पर झूठे क्षति दावों के विरुद्ध बचाव के लिए कोई आधार नहीं है। अभी 20 मिनट का निरीक्षण आपको बाद में 12,000 दिरहम के विवाद से बचाता है।"
      },
      {
        "title": "आप अपने ग्राहक के लिए एक नए किरायेदार को ऑनबोर्ड करने वाली एजेंसी हैं।",
        "body": "आपका मकान मालिक ग्राहक आपसे उनकी संपत्ति की रक्षा की उम्मीद करता है। आपकी एजेंसी के नाम के साथ ब्रांडेड एक हस्ताक्षरित चेक-इन निरीक्षण रिपोर्ट वह डिलीवरेबल है जो आपके प्रबंधन शुल्क को न्यायसंगत ठहराती है।"
      }
    ],
    "approach": "Snagify आपको 20 मिनट लेने वाले एक मानकीकृत चेक-इन प्रवाह से गुज़ारता है। आप पता दर्ज करते हैं (Ejari का स्वतः पता चलता है), कमरा-दर-कमरा घूमते हैं, ऐसी तस्वीरें लेते हैं जिन्हें AI स्वचालित रूप से क्षति के लिए टैग करता है, और दोहरे डिजिटल हस्ताक्षर के साथ समाप्त करते हैं। PDF रिपोर्ट RDC में मान्य है, SHA-256 के माध्यम से क्रिप्टोग्राफिक रूप से सत्यापन योग्य है, और कभी समाप्त नहीं होती।",
    "steps": [
      { "num": "01", "title": "Ejari का स्वतः पता लगाना", "body": "संपत्ति का पता दर्ज करें। Snagify Ejari पंजीकरण खींचता है और रिपोर्ट हेडर को पूर्व-भरता है।" },
      { "num": "02", "title": "कमरा-दर-कमरा घूमें", "body": "बैठक कक्ष, शयनकक्ष, रसोई, बाथरूम, बालकनी। प्रवाह स्टूडियो, अपार्टमेंट या विला के अनुकूल होता है।" },
      { "num": "03", "title": "हर चीज़ की तस्वीरें लें", "body": "हर कमरे में 3 से 8 तस्वीरें मिलती हैं। दीवारें, फ़र्श, फ़िक्स्चर, फ़िटिंग। शूट करते समय AI क्षति को टैग करता है।" },
      { "num": "04", "title": "इकाई विवरण नोट करें", "body": "उपकरण परीक्षण, चाबियाँ सौंपी गईं, AC सेवा तिथि, यदि लागू हो तो मीटर रीडिंग।" },
      { "num": "05", "title": "दोहरा डिजिटल हस्ताक्षर", "body": "मकान मालिक (या एजेंट) और किरायेदार दोनों एक ही डिवाइस पर हस्ताक्षर करते हैं। समय की मुहर क्रिप्टोग्राफिक रूप से लॉग की जाती हैं।" },
      { "num": "06", "title": "PDF प्राप्त करें", "body": "ब्रांडेड RDC में मान्य रिपोर्ट 60 सेकंड के भीतर ईमेल द्वारा दोनों पक्षों को पहुँचाई जाती है। चेक-इन पर मुफ़्त।" }
    ],
    "deliverable": "एक बहु-पृष्ठ PDF जिसमें संपत्ति विवरण के साथ कवर पेज, AI-टैग की गई स्थिति टिप्पणियों के साथ कमरा-दर-कमरा तस्वीर ग्रिड, समस्या सारांश, दोहरे हस्ताक्षर और एक SHA-256 सत्यापन हैश शामिल है। दुबई RDC और दीवानी अदालतों द्वारा जैसा है वैसा स्वीकार किया जाता है।",
    "faqs": [
      {
        "question": "चेक-इन निरीक्षण मुफ़्त क्यों हैं?",
        "answer": "बिना दस्तावेज़ीकरण वाला मूव-इन दुबई में जमानत राशि खोने का सबसे बड़ा कारण है। हम चाहते हैं कि हर किरायेदार और मकान मालिक को यह बुनियादी सुरक्षा मिले। आप केवल तभी क्रेडिट खर्च करते हैं जब आप चेक-आउट करते हैं।"
      },
      {
        "question": "Snagify चेक-इन में कितना समय लगता है?",
        "answer": "अधिकांश चेक-इन 1BR या 2BR अपार्टमेंट के लिए 20 से 25 मिनट चलते हैं। स्टूडियो तेज़ हैं (12 से 18 मिनट)। बड़े विला 40 से 60 मिनट तक ले सकते हैं।"
      },
      {
        "question": "क्या मकान मालिक को भी Snagify का उपयोग करना होगा?",
        "answer": "नहीं। कोई भी पक्ष चेक-इन निरीक्षण शुरू कर सकता है। एक बार जब आप शुरू करते हैं, तो आप दूसरे पक्ष के लिए अपने फ़ोन पर हस्ताक्षर करने के लिए एक हस्ताक्षर लिंक बनाते हैं। रिपोर्ट दोहरे हस्ताक्षरित होती है, चाहे मकान मालिक के पास Snagify खाता हो या नहीं।"
      },
      {
        "question": "यदि किरायेदार या मकान मालिक हस्ताक्षर करने से इनकार करे तो क्या?",
        "answer": "आप रिपोर्ट के अंदर सीधे इनकार का दस्तावेज़ीकरण करते हैं। एक समर्पित फ़ील्ड समय की मुहर और वैकल्पिक कारण के साथ इसे लॉग करता है। रिपोर्ट क़ानूनी रूप से वैध रहती है। एक दस्तावेज़ी इनकार मज़बूत प्रमाण है कि आपने उचित प्रक्रिया का पालन किया।"
      },
      {
        "question": "क्या चेक-इन रिपोर्ट पर्याप्त है, या मुझे चेक-आउट की भी आवश्यकता है?",
        "answer": "केवल चेक-इन आपको पहले से मौजूद क्षति के बारे में झूठे दावों से बचाता है। पट्टे के दौरान नई क्षति से बचाव के लिए, आपको मूव-आउट के समय एक चेक-आउट की भी आवश्यकता होगी। चेक-आउट सीधे चेक-इन आधार रेखा से तुलना करता है।"
      }
    ],
    "finalCta": {
      "headline": "अपने मूव-इन का दस्तावेज़ीकरण करें।",
      "subheadline": "मुफ़्त चेक-इन। RDC में मान्य। बिना क्रेडिट कार्ड के।",
      "buttonLabel": "मुफ़्त चेक-इन शुरू करें →"
    }
  },
  "check-out-inspection-dubai": {
    "slug": "check-out-inspection-dubai",
    "label": "चेक-आउट निरीक्षण",
    "fileName": "check-out-inspection-dubai",
    "metaTitle": "दुबई चेक-आउट निरीक्षण · अपनी जमानत राशि वापस पाएँ · Snagify",
    "metaDescription": "दुबई किराये के लिए RDC में मान्य चेक-आउट निरीक्षण। चेक-इन आधार रेखा से तुलना, AI तस्वीर विश्लेषण, दोहरे हस्ताक्षर। जमानत राशि 30 दिनों में निपटाएँ, 6 महीनों में नहीं।",
    "keywords": "चेक-आउट निरीक्षण दुबई, मूव-आउट निरीक्षण दुबई, दुबई चेक आउट रिपोर्ट, किराया चेक आउट दुबई, जमानत वापसी दुबई",
    "eyebrow": "उपयोग का मामला",
    "headline": "दुबई में चेक-आउट निरीक्षण।",
    "headlineHighlight": "दुबई में।",
    "subheadline": "आपकी जमानत राशि दाँव पर है। एक दस्तावेज़ी चेक-आउट, जो सीधे मूल चेक-इन के विरुद्ध तुलना की जाती है, विवादों को 6 महीनों के बजाय 30 दिनों में निपटाती है। Snagify तुलना को स्वचालित बनाता है।",
    "what": [
      "चेक-आउट निरीक्षण एक किरायेदारी के अंत में किया गया औपचारिक दौरा है, जो संपत्ति की वर्तमान स्थिति की तुलना उसकी मूल चेक-इन स्थिति से करता है। यह पहचानता है कि पट्टे के दौरान क्या बदला और सामान्य घिसाव से परे किसी भी क्षति के लिए ज़िम्मेदारी सौंपता है।",
      "दुबई में, चेक-आउट वह जगह है जहाँ जमानत राशि के लिए लड़ाई होती है। तुलनीय चेक-इन आधार रेखा के बिना, मकान मालिक दावा कर सकता है कि लगभग कुछ भी किरायेदार के कारण हुआ था। Snagify के साथ, हर चेक-आउट प्रत्यक्ष दृश्य तुलना के लिए मूल चेक-इन को स्वतः खींचता है।",
      "चेक-आउट प्रति निरीक्षण एक क्रेडिट का उपयोग करते हैं। रिपोर्ट RDC में मान्य है, क्रिप्टोग्राफिक रूप से सत्यापन योग्य है, और दुबई की दीवानी अदालतों में प्रमाण के रूप में स्वीकार की जाती है।"
    ],
    "scenarios": [
      {
        "title": "आपका पट्टा समाप्त हो रहा है और आप पूरी जमानत राशि वापस चाहते हैं।",
        "body": "एक दस्तावेज़ी चेक-आउट, दोनों पक्षों द्वारा हस्ताक्षरित, सबसे मज़बूत प्रमाण है जो आप प्रस्तुत कर सकते हैं। Snagify चेक-आउट प्रस्तुत करने वाले किरायेदारों को 80% मामलों में RDC में दर्ज़ किए बिना पूर्ण जमानत राशि वापस मिलती है।"
      },
      {
        "title": "आपको एक चेक-आउट पर हस्ताक्षर करने के लिए कहा जा रहा है जिसकी आपने समीक्षा नहीं की।",
        "body": "ऐसा न करें। एक Snagify चेक-आउट पर ज़ोर दें जो प्रत्यक्ष तुलना के लिए मूल चेक-इन खींचता है। यदि मूव-इन पर तस्वीरें ली गईं तो पहले से मौजूद क्षति आप पर नहीं थोपी जा सकती।"
      },
      {
        "title": "आपका मकान मालिक क्षति के बारे में अस्पष्ट दावे कर रहा है।",
        "body": "एक Snagify मूव-आउट हर दावे को तस्वीरों और हस्ताक्षरों के साथ दस्तावेज़ी होने के लिए मजबूर करता है। RDC में मान्य रिपोर्ट में अस्पष्ट दावों के लिए कोई जगह नहीं है। या तो क्षति प्रमाण के साथ मौजूद है, या नहीं है।"
      }
    ],
    "approach": "Snagify प्रत्यक्ष तुलना के लिए मूल चेक-इन निरीक्षण को स्वतः खींचता है। आप वही कमरों से गुज़रते हैं, तुलनीय तस्वीरें लेते हैं, और सिस्टम तब और अब के बीच परिवर्तनों को उजागर करता है। AI क्षति को चिह्नित करता है। दोहरे हस्ताक्षर रिपोर्ट को लॉक करते हैं। PDF में चेक-इन और चेक-आउट दोनों साथ-साथ शामिल हैं।",
    "steps": [
      { "num": "01", "title": "चेक-इन आधार रेखा खींचें", "body": "Snagify इस संपत्ति के लिए मूल चेक-इन को स्वतः लोड करता है। आप देखते हैं कि मूव-इन पर हर कमरा कैसा दिखता था।" },
      { "num": "02", "title": "वही प्रवाह में चलें", "body": "वही कमरे, वही क्रम, जहाँ संभव हो वही तस्वीर कोण। तुलना को आसान बनाने के लिए प्रवाह समान है।" },
      { "num": "03", "title": "वर्तमान स्थिति कैद करें", "body": "हर कमरे की तस्वीरें। AI चेक-इन से तुलना करता है और परिवर्तनों को चिह्नित करता है। नई क्षति स्वचालित रूप से उजागर की जाती है।" },
      { "num": "04", "title": "अंतर टैग करें", "body": "पहले से मौजूद क्षति अछूती रहती है। नई क्षति को मकान मालिक/किरायेदार चर्चा के लिए चिह्नित किया जाता है। हर टैग पर समय की मुहर लगती है और लॉग किया जाता है।" },
      { "num": "05", "title": "चर्चा करें और दस्तावेज़ी करें", "body": "दूसरे पक्ष के साथ निष्कर्षों के बारे में चलें। हर विवादित आइटम को एक नोट मिलता है। रिपोर्ट दोनों दृष्टिकोण रिकॉर्ड करती है।" },
      { "num": "06", "title": "दोहरा हस्ताक्षर और SHA-256 लॉक", "body": "दोनों पक्ष हस्ताक्षर करते हैं। रिपोर्ट क्रिप्टोग्राफिक रूप से लॉक हो जाती है। बाद में कोई भी संपादन SHA-256 हैश को अमान्य कर देगा, RDC को तुरंत दिखाई देगा।" },
      { "num": "07", "title": "जमानत राशि निपटाएँ", "body": "अधिकांश विवाद 7 दिनों के भीतर निपट जाते हैं जब दोनों पक्षों ने एक ही प्रमाण दस्तावेज़ पर हस्ताक्षर किए हों। RDC में दर्ज़ करने की आवश्यकता नहीं।" }
    ],
    "deliverable": "एक बहु-पृष्ठ PDF जिसमें संदर्भ के लिए मूल चेक-इन, वर्तमान स्थिति की तस्वीरें, बदले गए कमरों की साथ-साथ तुलना, चिह्नित नई क्षति के साथ समस्या सारांश, दोहरे हस्ताक्षर और SHA-256 हैश शामिल हैं। यदि आवश्यक हो तो दुबई RDC द्वारा जैसा है वैसा स्वीकार किया जाता है।",
    "faqs": [
      {
        "question": "क्या Snagify चेक-आउट करने के लिए मुझे चेक-इन पर Snagify का उपयोग करना चाहिए था?",
        "answer": "आदर्श रूप से हाँ। चेक-आउट निरीक्षण की मुख्य ताक़त एक दस्तावेज़ी चेक-इन आधार रेखा के विरुद्ध तुलना है। यदि आपका मूल चेक-इन Word या काग़ज़ पर था, तो आप अभी भी Snagify चेक-आउट कर सकते हैं, लेकिन आप स्वचालित साथ-साथ तुलना सुविधा खो देते हैं।"
      },
      {
        "question": "Snagify सामान्य घिसाव को कैसे संभालता है?",
        "answer": "Snagify सामान्य घिसाव के लिए RERA के दिशानिर्देशों का पालन करता है। AI क्षति को चिह्नित करता है लेकिन दोष नहीं देता। दोहरे-हस्ताक्षरित चर्चा अनुभाग वह जगह है जहाँ मकान मालिक और किरायेदार सहमत होते हैं कि क्या सामान्य घिसाव है बनाम क्या कटौती की आवश्यकता है। यदि कोई विवाद बढ़ता है तो RDC दोनों दृष्टिकोणों को तौलता है।"
      },
      {
        "question": "एक चेक-आउट जमानत राशि को कितनी जल्दी निपटाता है?",
        "answer": "जब दोनों पक्ष एक ही Snagify चेक-आउट रिपोर्ट पर हस्ताक्षर करते हैं, तो जमानत राशि आम तौर पर 5 से 10 दिनों के भीतर निपट जाती है। जब वे हस्ताक्षर नहीं करते, रिपोर्ट अभी भी मज़बूत RDC प्रमाण है और अधिकांश मामले 30 से 60 दिनों के भीतर बंद हो जाते हैं।"
      },
      {
        "question": "यदि किरायेदार दावा करे कि क्षति पहले से थी तो क्या?",
        "answer": "Snagify मूल चेक-इन को स्वतः खींचता है। यदि एक क्षतिग्रस्त वस्तु को चेक-इन पर उसी स्थिति में फ़ोटो खींचा गया था, तो सिस्टम इसे पहले से मौजूद के रूप में चिह्नित करता है। किरायेदार से इसके लिए शुल्क नहीं लिया जा सकता।"
      },
      {
        "question": "एक चेक-आउट की लागत कितनी है?",
        "answer": "प्रति चेक-आउट एक क्रेडिट। क्रेडिट पैक 6 क्रेडिट से शुरू होते हैं और कभी समाप्त नहीं होते। Pro योजनाएँ एजेंसियों और संपत्ति प्रबंधकों के लिए प्रति माह 15 से 50 क्रेडिट शामिल करती हैं।"
      }
    ],
    "finalCta": {
      "headline": "अपनी किरायेदारी को प्रमाण के साथ समाप्त करें।",
      "subheadline": "20 मिनट। RDC में मान्य। एक क्रेडिट।",
      "buttonLabel": "एक चेक-आउट चलाएँ →"
    }
  },
  "snagging-inspection-dubai": {
    "slug": "snagging-inspection-dubai",
    "label": "स्नैगिंग निरीक्षण",
    "fileName": "snagging-inspection-dubai",
    "metaTitle": "दुबई संपत्ति स्नैगिंग · AI-संचालित स्नैग सूची · Snagify",
    "metaDescription": "दुबई की नई इमारतों और किराए के लिए स्नैगिंग निरीक्षण। AI हर दोष को टैग करता है, एक डेवलपर-तैयार स्नैग सूची PDF उत्पन्न करता है। SHA-256 सत्यापित, RDC में मान्य। 49 दिरहम से।",
    "keywords": "संपत्ति स्नैगिंग दुबई, स्नैगिंग निरीक्षण दुबई, दुबई स्नैग सूची, नई इमारत स्नैगिंग दुबई, ऑफ़ प्लान स्नैगिंग",
    "eyebrow": "उपयोग का मामला",
    "headline": "दुबई में संपत्ति स्नैगिंग।",
    "headlineHighlight": "दुबई में।",
    "subheadline": "स्नैगिंग एक नई या हाल ही में पूर्ण संपत्ति में दोषों की पहचान करने का अभ्यास है। सही ढंग से किया गया, यह डेवलपर को आपकी शून्य लागत पर मुद्दों को ठीक करने के लिए मजबूर करता है। ग़लत किया गया, हर स्नैग आपका रखरखाव बिल बन जाता है।",
    "what": [
      "स्नैगिंग एक संपत्ति निरीक्षण है जो स्थिति के बजाय दोषों की पहचान पर केंद्रित है। यह सबसे आम तौर पर डेवलपर से सौंपने पर किया जाता है, लेकिन प्रमुख नवीनीकरण के बाद या हाल ही में पूर्ण इकाई में किरायेदार के मूव-इन से पहले भी किया जा सकता है।",
      "दुबई में, स्नैगिंग किसी भी नई इमारत के ख़रीदार के लिए एक महत्वपूर्ण क़दम है। डेवलपर्स एक दोष देयता अवधि (आमतौर पर 12 महीने) प्रदान करते हैं जिसके दौरान उन्हें मुद्दों को शून्य लागत पर ठीक करना होगा। स्नैगिंग रिपोर्ट उन मुद्दों के अस्तित्व का आपका प्रमाण है।",
      "Snagify का AI दुबई संपत्ति दोषों के हज़ारों पर प्रशिक्षित है। यह स्वचालित रूप से दीवार की दरारें, पेंट की ख़ामियाँ, टाइल चिप्स, सैनिटरी रिसाव, बिजली के मुद्दे और तैयारी की समस्याओं को चिह्नित करता है। PDF गंभीरता रेटिंग के साथ सीधे डेवलपर के पास जाता है।"
    ],
    "scenarios": [
      {
        "title": "आपने ऑफ़-प्लान ख़रीदा और इकाई पहुँचाई जा रही है।",
        "body": "सौंपने के पहले 2 हफ़्तों में स्नैगिंग 90% डेवलपर-ठीक करने योग्य दोषों को पकड़ती है। बहुत लंबा रुकें और डेवलपर तर्क देगा कि आपने उन्हें ख़ुद किया।"
      },
      {
        "title": "आपका नवीनीकरण अभी समाप्त हुआ और आप गुणवत्ता सत्यापित करना चाहते हैं।",
        "body": "ठेकेदार चीज़ें चूकते हैं। एक 30 मिनट का स्नैगिंग निरीक्षण एक पंच सूची उत्पन्न करता है जो उन्हें अंतिम भुगतान से पहले मुद्दों को ठीक करने के लिए जवाबदेह बनाती है।"
      },
      {
        "title": "आप एक हाल ही में पूर्ण इकाई को किराए पर सूचीबद्ध कर रहे हैं।",
        "body": "पहले किरायेदार के मूव-इन से पहले स्नैगिंग आपको बिल्डर दोषों के बारे में किरायेदार की शिकायतों से बचाती है। अभी आप जिन मुद्दों का दस्तावेज़ीकरण करते हैं वे अभी भी डेवलपर के बिल पर हैं।"
      }
    ],
    "approach": "Snagify का स्नैगिंग प्रवाह चेक-इन से अधिक गहन है। AI हर तस्वीर को दोषों (दीवार, पेंट, टाइल, फ़िनिश, फ़िक्स्चर, बिजली, सैनिटरी) के लिए स्कैन करता है और गंभीरता (कॉस्मेटिक, कार्यात्मक, अत्यावश्यक) को वर्गीकृत करता है। हर दोष को तस्वीरी प्रमाण, स्थान और एक अनुशंसित सुधार मिलता है। PDF सीधे डेवलपर या ठेकेदार के पास जाने के लिए संरचित है।",
    "steps": [
      { "num": "01", "title": "स्नैगिंग सत्र सेट करें", "body": "संपत्ति विवरण, प्राप्तकर्ता के रूप में डेवलपर या ठेकेदार। गंभीरता सीमा (डिफ़ॉल्ट: सब कुछ कॉस्मेटिक और ऊपर चिह्नित करें)।" },
      { "num": "02", "title": "कमरा-दर-कमरा घूमें", "body": "स्नैगिंग स्थिति जाँचों से अधिक गहन है। हर अलमारी खोलें, हर सॉकेट परीक्षण करें, हर नल चलाएँ। हर दोष अपनी ख़ुद की तस्वीर का हक़दार है।" },
      { "num": "03", "title": "AI हर तस्वीर स्कैन करता है", "body": "दीवार की दरारें, पेंट की धारियाँ, टाइल चिप्स, गुम ग्राउट, खरोंच वाले स्कर्टिंग, टूटे फ़िक्स्चर, उजागर तार। AI सब कुछ चिह्नित करता है।" },
      { "num": "04", "title": "गंभीरता वर्गीकरण", "body": "कॉस्मेटिक (पेंट, खरोंच), कार्यात्मक (रिसाव वाला नल, टूटा आउटलेट), अत्यावश्यक (पानी की क्षति, बिजली का ख़तरा)। प्रत्येक अलग से टैग किया गया।" },
      { "num": "05", "title": "डेवलपर पावती हस्ताक्षर", "body": "डेवलपर का प्रतिनिधि एक ही डिवाइस पर हस्ताक्षर करता है। हर स्नैग अब अपेक्षित समाधान तिथि के साथ औपचारिक रूप से स्वीकार किया जाता है।" },
      { "num": "06", "title": "समय के साथ समाधानों को ट्रैक करें", "body": "जैसे-जैसे डेवलपर हर स्नैग को ठीक करता है, उसे अनुवर्ती तस्वीर के साथ हल के रूप में चिह्नित करें। अंतिम रिपोर्ट दिखाती है कि क्या ठीक किया गया और क्या नहीं।" }
    ],
    "deliverable": "एक बहु-पृष्ठ स्नैग सूची PDF जिसमें हर दोष की तस्वीरें, गंभीरता वर्गीकरण, कमरा-दर-कमरा संगठन, डेवलपर पावती हस्ताक्षर और एक समाधान ट्रैकर शामिल हैं। यदि आवश्यक हो तो डेवलपर की ग्राहक सेवा टीम को सीधे भेजने या RERA को बढ़ाने के लिए उपयुक्त।",
    "faqs": [
      {
        "question": "मुझे स्नैगिंग निरीक्षण कब करना चाहिए?",
        "answer": "ऑफ़-प्लान ख़रीद के लिए सौंपने के 2 हफ़्तों के भीतर। नवीनीकरण के लिए ठेकेदार के पूरा होने के 1 हफ़्ते के भीतर। एक नई इकाई को किराए पर सूचीबद्ध करने से पहले। जितनी जल्दी हो उतना अच्छा, क्योंकि डेवलपर्स अक्सर तर्क देते हैं कि यदि आप बहुत लंबा रुकते हैं तो दोष सौंपने के बाद दिखाई दिए।"
      },
      {
        "question": "स्नैगिंग और चेक-इन में क्या अंतर है?",
        "answer": "एक चेक-इन एक किरायेदारी आधार रेखा के लिए स्थिति का दस्तावेज़ीकरण करता है। स्नैगिंग दोषों का दस्तावेज़ीकरण करता है जो डेवलपर या ठेकेदार द्वारा आपकी शून्य लागत पर ठीक किए जाने चाहिए। वे प्रवाह में ओवरलैप करते हैं लेकिन रिपोर्ट संरचना और प्राप्तकर्ता अलग हैं।"
      },
      {
        "question": "क्या AI वास्तविक दोष चूक सकता है?",
        "answer": "AI तस्वीरों में अधिकांश दृश्य दोषों को पकड़ता है। यह तस्वीर में कैद नहीं की गई किसी भी चीज़ को चूक सकता है (सूक्ष्म गंध, कमज़ोर ध्वनि, रुक-रुक कर मुद्दे)। तस्वीरें उदारता से लें और हर कमरे में सावधानी से चलें। मानव आँख और AI मिलकर लगभग सब कुछ पकड़ते हैं।"
      },
      {
        "question": "एक स्नैग सूची कितनी बड़ी होनी चाहिए?",
        "answer": "यह भिन्न होती है। एक नई इमारत ऑफ़-प्लान इकाई में आम तौर पर डेवलपर की गुणवत्ता के आधार पर सौंपने पर 30 से 80 स्नैग होते हैं। एक नवीनीकृत इकाई में आमतौर पर 10 से 30 होते हैं। यदि आप शून्य देख रहे हैं, तो आप शायद ध्यान से नहीं देख रहे।"
      },
      {
        "question": "यदि डेवलपर मेरी स्नैग सूची को नज़रअंदाज़ करे तो क्या?",
        "answer": "अधिकांश प्रतिष्ठित दुबई डेवलपर्स 14 से 30 दिनों के भीतर जवाब देते हैं। यदि आपका नहीं देता, तो RERA को बढ़ाएँ। SHA-256 हैश और डेवलपर के पावती हस्ताक्षर के साथ Snagify PDF एक RERA शिकायत में मज़बूत प्रमाण है।"
      }
    ],
    "finalCta": {
      "headline": "हर दोष पकड़ें।",
      "subheadline": "AI-संचालित स्नैगिंग। मुफ़्त चेक-इन। केवल स्नैग रिपोर्ट के लिए भुगतान करें।",
      "buttonLabel": "एक स्नैग सूची शुरू करें →"
    }
  }
}